Workbook

Sheet Параметры
A1: Параметр | B1: Значение | C1: Комментарий
A2: Курс USD→EUR | B2: 0.92 | C2: консервативный
A3: НДС Германия | B3: 0.19 | C3: изъят из розничной цены
A4: Referral Amazon | B4: 0.15 | C4: категории портфеля
A5: PPC по умолчанию (запуск) | B5: 0.12 | C5: Jura 10%, B2B 5% — заданы в листе Модель
A6: Возвраты | B6: 0.02 | C6: % от цены
A7: Преп/маркировка €/шт | B7: 0.3
A8: QC/брак | B8: 0.03 | C8: % от FOB
A9: Целевая маржа A | B9: 0.25 | C9: порог «Закупка ≤»
A10: Целевая маржа B (минимум) | B10: 0.2 | C10: порог отмены SKU: <15% на факт. landed
A11: Разгон: доля цели в первые 90 дней | B11: 0.4 | C11: для P&L пилота
A13: Желтые ячейки — редактируйте (параметры и котировки). Зеленоватые — формулы, пересчет автоматический.

Sheet Модель SKU
A1: SKU | B1: Волна | C1: Цена € | D1: FBA € | E1: Хран. € | F1: PPC % | G1: FOB $ (котировка) | H1: Фрахт €/шт | I1: Пошлина % | J1: Нетто € | K1: Referral € | L1: PPC € | M1: Возвраты € | N1: Landed € | O1: Прибыль €/шт | P1: Маржа % | Q1: ROI % | R1: FOB ≤ (25%) | S1: FOB ≤ (20%) | T1: Безубыток € | U1: Партия, шт | V1: Цель, шт/мес | W1: Прибыль €/мес
A2: Фильтр Jura RFID 6er | B2: В1 | C2: 42.99 | D2: 3.46 | E2: 0.4 | F2: 0.1 | G2: 10 | H2: 0.5 | I2: 0.035 | J2: =C2/(1+Параметры!$B$3) | K2: =C2*Параметры!$B$4 | L2: =C2*F2 | M2: =C2*Параметры!$B$6 | N2: =G2*Параметры!$B$2*(1+I2+Параметры!$B$8)+H2+Параметры!$B$7 | O2: =J2-K2-D2-E2-L2-M2-N2 | P2: =O2/C2 | Q2: =O2/N2 | R2: =(J2-K2-D2-E2-L2-M2-Параметры!$B$9*C2-H2-Параметры!$B$7)/(Параметры!$B$2*(1+I2+Параметры!$B$8)) | S2: =(J2-K2-D2-E2-L2-M2-Параметры!$B$10*C2-H2-Параметры!$B$7)/(Параметры!$B$2*(1+I2+Параметры!$B$8)) | T2: =(D2+E2+N2)/(1/(1+Параметры!$B$3)-(Параметры!$B$4+F2+Параметры!$B$6)) | U2: 500 | V2: 500 | W2: =O2*V2
A3: Фильтр DeLonghi 6er | B3: В1 | C3: 24.99 | D3: 3.47 | E3: 0.4 | F3: 0.12 | G3: 4 | H3: 0.5 | I3: 0.035 | J3: =C3/(1+Параметры!$B$3) | K3: =C3*Параметры!$B$4 | L3: =C3*F3 | M3: =C3*Параметры!$B$6 | N3: =G3*Параметры!$B$2*(1+I3+Параметры!$B$8)+H3+Параметры!$B$7 | O3: =J3-K3-D3-E3-L3-M3-N3 | P3: =O3/C3 | Q3: =O3/N3 | R3: =(J3-K3-D3-E3-L3-M3-Параметры!$B$9*C3-H3-Параметры!$B$7)/(Параметры!$B$2*(1+I3+Параметры!$B$8)) | S3: =(J3-K3-D3-E3-L3-M3-Параметры!$B$10*C3-H3-Параметры!$B$7)/(Параметры!$B$2*(1+I3+Параметры!$B$8)) | T3: =(D3+E3+N3)/(1/(1+Параметры!$B$3)-(Параметры!$B$4+F3+Параметры!$B$6)) | U3: 500 | V3: 600 | W3: =O3*V3
A4: Kühltasche 40L | B4: В1 | C4: 34.99 | D4: 4.59 | E4: 0.45 | F4: 0.12 | G4: 4.5 | H4: 0.9 | I4: 0.097 | J4: =C4/(1+Параметры!$B$3) | K4: =C4*Параметры!$B$4 | L4: =C4*F4 | M4: =C4*Параметры!$B$6 | N4: =G4*Параметры!$B$2*(1+I4+Параметры!$B$8)+H4+Параметры!$B$7 | O4: =J4-K4-D4-E4-L4-M4-N4 | P4: =O4/C4 | Q4: =O4/N4 | R4: =(J4-K4-D4-E4-L4-M4-Параметры!$B$9*C4-H4-Параметры!$B$7)/(Параметры!$B$2*(1+I4+Параметры!$B$8)) | S4: =(J4-K4-D4-E4-L4-M4-Параметры!$B$10*C4-H4-Параметры!$B$7)/(Параметры!$B$2*(1+I4+Параметры!$B$8)) | T4: =(D4+E4+N4)/(1/(1+Параметры!$B$3)-(Параметры!$B$4+F4+Параметры!$B$6)) | U4: 500 | V4: 300 | W4: =O4*V4
A5: Brotbeutel 2er | B5: В1 | C5: 19.99 | D5: 3.08 | E5: 0.35 | F5: 0.12 | G5: 2.2 | H5: 0.4 | I5: 0.12 | J5: =C5/(1+Параметры!$B$3) | K5: =C5*Параметры!$B$4 | L5: =C5*F5 | M5: =C5*Параметры!$B$6 | N5: =G5*Параметры!$B$2*(1+I5+Параметры!$B$8)+H5+Параметры!$B$7 | O5: =J5-K5-D5-E5-L5-M5-N5 | P5: =O5/C5 | Q5: =O5/N5 | R5: =(J5-K5-D5-E5-L5-M5-Параметры!$B$9*C5-H5-Параметры!$B$7)/(Параметры!$B$2*(1+I5+Параметры!$B$8)) | S5: =(J5-K5-D5-E5-L5-M5-Параметры!$B$10*C5-H5-Параметры!$B$7)/(Параметры!$B$2*(1+I5+Параметры!$B$8)) | T5: =(D5+E5+N5)/(1/(1+Параметры!$B$3)-(Параметры!$B$4+F5+Параметры!$B$6)) | U5: 500 | V5: 180 | W5: =O5*V5
A6: TV-стенд CT7501 | B6: Страт | C6: 149.99 | D6: 14.11 | E6: 3.5 | F6: 0.1 | G6: 29.7 | H6: 3.3 | I6: 0 | J6: =C6/(1+Параметры!$B$3) | K6: =C6*Параметры!$B$4 | L6: =C6*F6 | M6: =C6*Параметры!$B$6 | N6: =G6*Параметры!$B$2*(1+I6+Параметры!$B$8)+H6+Параметры!$B$7 | O6: =J6-K6-D6-E6-L6-M6-N6 | P6: =O6/C6 | Q6: =O6/N6 | R6: =(J6-K6-D6-E6-L6-M6-Параметры!$B$9*C6-H6-Параметры!$B$7)/(Параметры!$B$2*(1+I6+Параметры!$B$8)) | S6: =(J6-K6-D6-E6-L6-M6-Параметры!$B$10*C6-H6-Параметры!$B$7)/(Параметры!$B$2*(1+I6+Параметры!$B$8)) | T6: =(D6+E6+N6)/(1/(1+Параметры!$B$3)-(Параметры!$B$4+F6+Параметры!$B$6)) | U6: 200 | V6: 75 | W6: =O6*V6
A7: Картотека ZY-3 | B7: Страт | C7: 219 | D7: 25 | E7: 5 | F7: 0.05 | G7: 45 | H7: 22 | I7: 0 | J7: =C7/(1+Параметры!$B$3) | K7: =C7*Параметры!$B$4 | L7: =C7*F7 | M7: =C7*Параметры!$B$6 | N7: =G7*Параметры!$B$2*(1+I7+Параметры!$B$8)+H7+Параметры!$B$7 | O7: =J7-K7-D7-E7-L7-M7-N7 | P7: =O7/C7 | Q7: =O7/N7 | R7: =(J7-K7-D7-E7-L7-M7-Параметры!$B$9*C7-H7-Параметры!$B$7)/(Параметры!$B$2*(1+I7+Параметры!$B$8)) | S7: =(J7-K7-D7-E7-L7-M7-Параметры!$B$10*C7-H7-Параметры!$B$7)/(Параметры!$B$2*(1+I7+Параметры!$B$8)) | T7: =(D7+E7+N7)/(1/(1+Параметры!$B$3)-(Параметры!$B$4+F7+Параметры!$B$6)) | U7: 40 | V7: 21 | W7: =O7*V7
A8: Kirschentkerner | B8: В2 | C8: 45.99 | D8: 3.86 | E8: 0.45 | F8: 0.12 | G8: 5 | H8: 0.7 | I8: 0.085 | J8: =C8/(1+Параметры!$B$3) | K8: =C8*Параметры!$B$4 | L8: =C8*F8 | M8: =C8*Параметры!$B$6 | N8: =G8*Параметры!$B$2*(1+I8+Параметры!$B$8)+H8+Параметры!$B$7 | O8: =J8-K8-D8-E8-L8-M8-N8 | P8: =O8/C8 | Q8: =O8/N8 | R8: =(J8-K8-D8-E8-L8-M8-Параметры!$B$9*C8-H8-Параметры!$B$7)/(Параметры!$B$2*(1+I8+Параметры!$B$8)) | S8: =(J8-K8-D8-E8-L8-M8-Параметры!$B$10*C8-H8-Параметры!$B$7)/(Параметры!$B$2*(1+I8+Параметры!$B$8)) | T8: =(D8+E8+N8)/(1/(1+Параметры!$B$3)-(Параметры!$B$4+F8+Параметры!$B$6)) | U8: 500 | V8: 400 | W8: =O8*V8
A9: Fliegengitter 4er | B9: В2 | C9: 39.99 | D9: 5.48 | E9: 0.5 | F9: 0.12 | G9: 6.5 | H9: 1.25 | I9: 0.065 | J9: =C9/(1+Параметры!$B$3) | K9: =C9*Параметры!$B$4 | L9: =C9*F9 | M9: =C9*Параметры!$B$6 | N9: =G9*Параметры!$B$2*(1+I9+Параметры!$B$8)+H9+Параметры!$B$7 | O9: =J9-K9-D9-E9-L9-M9-N9 | P9: =O9/C9 | Q9: =O9/N9 | R9: =(J9-K9-D9-E9-L9-M9-Параметры!$B$9*C9-H9-Параметры!$B$7)/(Параметры!$B$2*(1+I9+Параметры!$B$8)) | S9: =(J9-K9-D9-E9-L9-M9-Параметры!$B$10*C9-H9-Параметры!$B$7)/(Параметры!$B$2*(1+I9+Параметры!$B$8)) | T9: =(D9+E9+N9)/(1/(1+Параметры!$B$3)-(Параметры!$B$4+F9+Параметры!$B$6)) | U9: 500 | V9: 300 | W9: =O9*V9
A10: Kühldecke Arc-Chill | B10: В2 | C10: 42.99 | D10: 4.42 | E10: 0.6 | F10: 0.12 | G10: 8.5 | H10: 1 | I10: 0.12 | J10: =C10/(1+Параметры!$B$3) | K10: =C10*Параметры!$B$4 | L10: =C10*F10 | M10: =C10*Параметры!$B$6 | N10: =G10*Параметры!$B$2*(1+I10+Параметры!$B$8)+H10+Параметры!$B$7 | O10: =J10-K10-D10-E10-L10-M10-N10 | P10: =O10/C10 | Q10: =O10/N10 | R10: =(J10-K10-D10-E10-L10-M10-Параметры!$B$9*C10-H10-Параметры!$B$7)/(Параметры!$B$2*(1+I10+Параметры!$B$8)) | S10: =(J10-K10-D10-E10-L10-M10-Параметры!$B$10*C10-H10-Параметры!$B$7)/(Параметры!$B$2*(1+I10+Параметры!$B$8)) | T10: =(D10+E10+N10)/(1/(1+Параметры!$B$3)-(Параметры!$B$4+F10+Параметры!$B$6)) | U10: 300 | V10: 225 | W10: =O10*V10
A11: ИТОГО портфель | W11: =SUM(W2:W10)

Sheet Сценарии
A1: SKU | B1: Сценарий | C1: Цена × | D1: FOB × | E1: PPC % | F1: Цена € | G1: FOB $ | H1: Landed € | I1: Прибыль €/шт | J1: Маржа % | K1: Прибыль €/мес (цель шт)
A2: ='Модель SKU'!A2 | B2: Пессимист: демпинг −10% цены, FOB +20%, PPC 15% | C2: 0.9 | D2: 1.2 | E2: 0.15 | F2: ='Модель SKU'!C2*C2 | G2: ='Модель SKU'!G2*D2 | H2: =G2*Параметры!$B$2*(1+'Модель SKU'!I2+Параметры!$B$8)+'Модель SKU'!H2+Параметры!$B$7 | I2: =F2/(1+Параметры!$B$3)-F2*Параметры!$B$4-'Модель SKU'!D2-'Модель SKU'!E2-F2*E2-F2*Параметры!$B$6-H2 | J2: =I2/F2 | K2: =I2*'Модель SKU'!V2
A3: ='Модель SKU'!A2 | B3: База (= лист Модель) | C3: 1 | D3: 1 | E3: ='Модель SKU'!F2 | F3: ='Модель SKU'!C2*C3 | G3: ='Модель SKU'!G2*D3 | H3: =G3*Параметры!$B$2*(1+'Модель SKU'!I2+Параметры!$B$8)+'Модель SKU'!H2+Параметры!$B$7 | I3: =F3/(1+Параметры!$B$3)-F3*Параметры!$B$4-'Модель SKU'!D2-'Модель SKU'!E2-F3*E3-F3*Параметры!$B$6-H3 | J3: =I3/F3 | K3: =I3*'Модель SKU'!V2
A4: ='Модель SKU'!A2 | B4: Оптимист: цена база, FOB −10%, PPC 8% | C4: 1 | D4: 0.9 | E4: 0.08 | F4: ='Модель SKU'!C2*C4 | G4: ='Модель SKU'!G2*D4 | H4: =G4*Параметры!$B$2*(1+'Модель SKU'!I2+Параметры!$B$8)+'Модель SKU'!H2+Параметры!$B$7 | I4: =F4/(1+Параметры!$B$3)-F4*Параметры!$B$4-'Модель SKU'!D2-'Модель SKU'!E2-F4*E4-F4*Параметры!$B$6-H4 | J4: =I4/F4 | K4: =I4*'Модель SKU'!V2
A5: ='Модель SKU'!A3 | B5: Пессимист: демпинг −10% цены, FOB +20%, PPC 15% | C5: 0.9 | D5: 1.2 | E5: 0.15 | F5: ='Модель SKU'!C3*C5 | G5: ='Модель SKU'!G3*D5 | H5: =G5*Параметры!$B$2*(1+'Модель SKU'!I3+Параметры!$B$8)+'Модель SKU'!H3+Параметры!$B$7 | I5: =F5/(1+Параметры!$B$3)-F5*Параметры!$B$4-'Модель SKU'!D3-'Модель SKU'!E3-F5*E5-F5*Параметры!$B$6-H5 | J5: =I5/F5 | K5: =I5*'Модель SKU'!V3
A6: ='Модель SKU'!A3 | B6: База (= лист Модель) | C6: 1 | D6: 1 | E6: ='Модель SKU'!F3 | F6: ='Модель SKU'!C3*C6 | G6: ='Модель SKU'!G3*D6 | H6: =G6*Параметры!$B$2*(1+'Модель SKU'!I3+Параметры!$B$8)+'Модель SKU'!H3+Параметры!$B$7 | I6: =F6/(1+Параметры!$B$3)-F6*Параметры!$B$4-'Модель SKU'!D3-'Модель SKU'!E3-F6*E6-F6*Параметры!$B$6-H6 | J6: =I6/F6 | K6: =I6*'Модель SKU'!V3
A7: ='Модель SKU'!A3 | B7: Оптимист: цена база, FOB −10%, PPC 8% | C7: 1 | D7: 0.9 | E7: 0.08 | F7: ='Модель SKU'!C3*C7 | G7: ='Модель SKU'!G3*D7 | H7: =G7*Параметры!$B$2*(1+'Модель SKU'!I3+Параметры!$B$8)+'Модель SKU'!H3+Параметры!$B$7 | I7: =F7/(1+Параметры!$B$3)-F7*Параметры!$B$4-'Модель SKU'!D3-'Модель SKU'!E3-F7*E7-F7*Параметры!$B$6-H7 | J7: =I7/F7 | K7: =I7*'Модель SKU'!V3
A8: ='Модель SKU'!A4 | B8: Пессимист: демпинг −10% цены, FOB +20%, PPC 15% | C8: 0.9 | D8: 1.2 | E8: 0.15 | F8: ='Модель SKU'!C4*C8 | G8: ='Модель SKU'!G4*D8 | H8: =G8*Параметры!$B$2*(1+'Модель SKU'!I4+Параметры!$B$8)+'Модель SKU'!H4+Параметры!$B$7 | I8: =F8/(1+Параметры!$B$3)-F8*Параметры!$B$4-'Модель SKU'!D4-'Модель SKU'!E4-F8*E8-F8*Параметры!$B$6-H8 | J8: =I8/F8 | K8: =I8*'Модель SKU'!V4
A9: ='Модель SKU'!A4 | B9: База (= лист Модель) | C9: 1 | D9: 1 | E9: ='Модель SKU'!F4 | F9: ='Модель SKU'!C4*C9 | G9: ='Модель SKU'!G4*D9 | H9: =G9*Параметры!$B$2*(1+'Модель SKU'!I4+Параметры!$B$8)+'Модель SKU'!H4+Параметры!$B$7 | I9: =F9/(1+Параметры!$B$3)-F9*Параметры!$B$4-'Модель SKU'!D4-'Модель SKU'!E4-F9*E9-F9*Параметры!$B$6-H9 | J9: =I9/F9 | K9: =I9*'Модель SKU'!V4
A10: ='Модель SKU'!A4 | B10: Оптимист: цена база, FOB −10%, PPC 8% | C10: 1 | D10: 0.9 | E10: 0.08 | F10: ='Модель SKU'!C4*C10 | G10: ='Модель SKU'!G4*D10 | H10: =G10*Параметры!$B$2*(1+'Модель SKU'!I4+Параметры!$B$8)+'Модель SKU'!H4+Параметры!$B$7 | I10: =F10/(1+Параметры!$B$3)-F10*Параметры!$B$4-'Модель SKU'!D4-'Модель SKU'!E4-F10*E10-F10*Параметры!$B$6-H10 | J10: =I10/F10 | K10: =I10*'Модель SKU'!V4
A11: ='Модель SKU'!A5 | B11: Пессимист: демпинг −10% цены, FOB +20%, PPC 15% | C11: 0.9 | D11: 1.2 | E11: 0.15 | F11: ='Модель SKU'!C5*C11 | G11: ='Модель SKU'!G5*D11 | H11: =G11*Параметры!$B$2*(1+'Модель SKU'!I5+Параметры!$B$8)+'Модель SKU'!H5+Параметры!$B$7 | I11: =F11/(1+Параметры!$B$3)-F11*Параметры!$B$4-'Модель SKU'!D5-'Модель SKU'!E5-F11*E11-F11*Параметры!$B$6-H11 | J11: =I11/F11 | K11: =I11*'Модель SKU'!V5
A12: ='Модель SKU'!A5 | B12: База (= лист Модель) | C12: 1 | D12: 1 | E12: ='Модель SKU'!F5 | F12: ='Модель SKU'!C5*C12 | G12: ='Модель SKU'!G5*D12 | H12: =G12*Параметры!$B$2*(1+'Модель SKU'!I5+Параметры!$B$8)+'Модель SKU'!H5+Параметры!$B$7 | I12: =F12/(1+Параметры!$B$3)-F12*Параметры!$B$4-'Модель SKU'!D5-'Модель SKU'!E5-F12*E12-F12*Параметры!$B$6-H12 | J12: =I12/F12 | K12: =I12*'Модель SKU'!V5
A13: ='Модель SKU'!A5 | B13: Оптимист: цена база, FOB −10%, PPC 8% | C13: 1 | D13: 0.9 | E13: 0.08 | F13: ='Модель SKU'!C5*C13 | G13: ='Модель SKU'!G5*D13 | H13: =G13*Параметры!$B$2*(1+'Модель SKU'!I5+Параметры!$B$8)+'Модель SKU'!H5+Параметры!$B$7 | I13: =F13/(1+Параметры!$B$3)-F13*Параметры!$B$4-'Модель SKU'!D5-'Модель SKU'!E5-F13*E13-F13*Параметры!$B$6-H13 | J13: =I13/F13 | K13: =I13*'Модель SKU'!V5
A14: ='Модель SKU'!A6 | B14: Пессимист: демпинг −10% цены, FOB +20%, PPC 15% | C14: 0.9 | D14: 1.2 | E14: 0.15 | F14: ='Модель SKU'!C6*C14 | G14: ='Модель SKU'!G6*D14 | H14: =G14*Параметры!$B$2*(1+'Модель SKU'!I6+Параметры!$B$8)+'Модель SKU'!H6+Параметры!$B$7 | I14: =F14/(1+Параметры!$B$3)-F14*Параметры!$B$4-'Модель SKU'!D6-'Модель SKU'!E6-F14*E14-F14*Параметры!$B$6-H14 | J14: =I14/F14 | K14: =I14*'Модель SKU'!V6
A15: ='Модель SKU'!A6 | B15: База (= лист Модель) | C15: 1 | D15: 1 | E15: ='Модель SKU'!F6 | F15: ='Модель SKU'!C6*C15 | G15: ='Модель SKU'!G6*D15 | H15: =G15*Параметры!$B$2*(1+'Модель SKU'!I6+Параметры!$B$8)+'Модель SKU'!H6+Параметры!$B$7 | I15: =F15/(1+Параметры!$B$3)-F15*Параметры!$B$4-'Модель SKU'!D6-'Модель SKU'!E6-F15*E15-F15*Параметры!$B$6-H15 | J15: =I15/F15 | K15: =I15*'Модель SKU'!V6
A16: ='Модель SKU'!A6 | B16: Оптимист: цена база, FOB −10%, PPC 8% | C16: 1 | D16: 0.9 | E16: 0.08 | F16: ='Модель SKU'!C6*C16 | G16: ='Модель SKU'!G6*D16 | H16: =G16*Параметры!$B$2*(1+'Модель SKU'!I6+Параметры!$B$8)+'Модель SKU'!H6+Параметры!$B$7 | I16: =F16/(1+Параметры!$B$3)-F16*Параметры!$B$4-'Модель SKU'!D6-'Модель SKU'!E6-F16*E16-F16*Параметры!$B$6-H16 | J16: =I16/F16 | K16: =I16*'Модель SKU'!V6
A17: ='Модель SKU'!A7 | B17: Пессимист: демпинг −10% цены, FOB +20%, PPC 15% | C17: 0.9 | D17: 1.2 | E17: 0.15 | F17: ='Модель SKU'!C7*C17 | G17: ='Модель SKU'!G7*D17 | H17: =G17*Параметры!$B$2*(1+'Модель SKU'!I7+Параметры!$B$8)+'Модель SKU'!H7+Параметры!$B$7 | I17: =F17/(1+Параметры!$B$3)-F17*Параметры!$B$4-'Модель SKU'!D7-'Модель SKU'!E7-F17*E17-F17*Параметры!$B$6-H17 | J17: =I17/F17 | K17: =I17*'Модель SKU'!V7
A18: ='Модель SKU'!A7 | B18: База (= лист Модель) | C18: 1 | D18: 1 | E18: ='Модель SKU'!F7 | F18: ='Модель SKU'!C7*C18 | G18: ='Модель SKU'!G7*D18 | H18: =G18*Параметры!$B$2*(1+'Модель SKU'!I7+Параметры!$B$8)+'Модель SKU'!H7+Параметры!$B$7 | I18: =F18/(1+Параметры!$B$3)-F18*Параметры!$B$4-'Модель SKU'!D7-'Модель SKU'!E7-F18*E18-F18*Параметры!$B$6-H18 | J18: =I18/F18 | K18: =I18*'Модель SKU'!V7
A19: ='Модель SKU'!A7 | B19: Оптимист: цена база, FOB −10%, PPC 8% | C19: 1 | D19: 0.9 | E19: 0.08 | F19: ='Модель SKU'!C7*C19 | G19: ='Модель SKU'!G7*D19 | H19: =G19*Параметры!$B$2*(1+'Модель SKU'!I7+Параметры!$B$8)+'Модель SKU'!H7+Параметры!$B$7 | I19: =F19/(1+Параметры!$B$3)-F19*Параметры!$B$4-'Модель SKU'!D7-'Модель SKU'!E7-F19*E19-F19*Параметры!$B$6-H19 | J19: =I19/F19 | K19: =I19*'Модель SKU'!V7
A20: ='Модель SKU'!A8 | B20: Пессимист: демпинг −10% цены, FOB +20%, PPC 15% | C20: 0.9 | D20: 1.2 | E20: 0.15 | F20: ='Модель SKU'!C8*C20 | G20: ='Модель SKU'!G8*D20 | H20: =G20*Параметры!$B$2*(1+'Модель SKU'!I8+Параметры!$B$8)+'Модель SKU'!H8+Параметры!$B$7 | I20: =F20/(1+Параметры!$B$3)-F20*Параметры!$B$4-'Модель SKU'!D8-'Модель SKU'!E8-F20*E20-F20*Параметры!$B$6-H20 | J20: =I20/F20 | K20: =I20*'Модель SKU'!V8
A21: ='Модель SKU'!A8 | B21: База (= лист Модель) | C21: 1 | D21: 1 | E21: ='Модель SKU'!F8 | F21: ='Модель SKU'!C8*C21 | G21: ='Модель SKU'!G8*D21 | H21: =G21*Параметры!$B$2*(1+'Модель SKU'!I8+Параметры!$B$8)+'Модель SKU'!H8+Параметры!$B$7 | I21: =F21/(1+Параметры!$B$3)-F21*Параметры!$B$4-'Модель SKU'!D8-'Модель SKU'!E8-F21*E21-F21*Параметры!$B$6-H21 | J21: =I21/F21 | K21: =I21*'Модель SKU'!V8
A22: ='Модель SKU'!A8 | B22: Оптимист: цена база, FOB −10%, PPC 8% | C22: 1 | D22: 0.9 | E22: 0.08 | F22: ='Модель SKU'!C8*C22 | G22: ='Модель SKU'!G8*D22 | H22: =G22*Параметры!$B$2*(1+'Модель SKU'!I8+Параметры!$B$8)+'Модель SKU'!H8+Параметры!$B$7 | I22: =F22/(1+Параметры!$B$3)-F22*Параметры!$B$4-'Модель SKU'!D8-'Модель SKU'!E8-F22*E22-F22*Параметры!$B$6-H22 | J22: =I22/F22 | K22: =I22*'Модель SKU'!V8
A23: ='Модель SKU'!A9 | B23: Пессимист: демпинг −10% цены, FOB +20%, PPC 15% | C23: 0.9 | D23: 1.2 | E23: 0.15 | F23: ='Модель SKU'!C9*C23 | G23: ='Модель SKU'!G9*D23 | H23: =G23*Параметры!$B$2*(1+'Модель SKU'!I9+Параметры!$B$8)+'Модель SKU'!H9+Параметры!$B$7 | I23: =F23/(1+Параметры!$B$3)-F23*Параметры!$B$4-'Модель SKU'!D9-'Модель SKU'!E9-F23*E23-F23*Параметры!$B$6-H23 | J23: =I23/F23 | K23: =I23*'Модель SKU'!V9
A24: ='Модель SKU'!A9 | B24: База (= лист Модель) | C24: 1 | D24: 1 | E24: ='Модель SKU'!F9 | F24: ='Модель SKU'!C9*C24 | G24: ='Модель SKU'!G9*D24 | H24: =G24*Параметры!$B$2*(1+'Модель SKU'!I9+Параметры!$B$8)+'Модель SKU'!H9+Параметры!$B$7 | I24: =F24/(1+Параметры!$B$3)-F24*Параметры!$B$4-'Модель SKU'!D9-'Модель SKU'!E9-F24*E24-F24*Параметры!$B$6-H24 | J24: =I24/F24 | K24: =I24*'Модель SKU'!V9
A25: ='Модель SKU'!A9 | B25: Оптимист: цена база, FOB −10%, PPC 8% | C25: 1 | D25: 0.9 | E25: 0.08 | F25: ='Модель SKU'!C9*C25 | G25: ='Модель SKU'!G9*D25 | H25: =G25*Параметры!$B$2*(1+'Модель SKU'!I9+Параметры!$B$8)+'Модель SKU'!H9+Параметры!$B$7 | I25: =F25/(1+Параметры!$B$3)-F25*Параметры!$B$4-'Модель SKU'!D9-'Модель SKU'!E9-F25*E25-F25*Параметры!$B$6-H25 | J25: =I25/F25 | K25: =I25*'Модель SKU'!V9
A26: ='Модель SKU'!A10 | B26: Пессимист: демпинг −10% цены, FOB +20%, PPC 15% | C26: 0.9 | D26: 1.2 | E26: 0.15 | F26: ='Модель SKU'!C10*C26 | G26: ='Модель SKU'!G10*D26 | H26: =G26*Параметры!$B$2*(1+'Модель SKU'!I10+Параметры!$B$8)+'Модель SKU'!H10+Параметры!$B$7 | I26: =F26/(1+Параметры!$B$3)-F26*Параметры!$B$4-'Модель SKU'!D10-'Модель SKU'!E10-F26*E26-F26*Параметры!$B$6-H26 | J26: =I26/F26 | K26: =I26*'Модель SKU'!V10
A27: ='Модель SKU'!A10 | B27: База (= лист Модель) | C27: 1 | D27: 1 | E27: ='Модель SKU'!F10 | F27: ='Модель SKU'!C10*C27 | G27: ='Модель SKU'!G10*D27 | H27: =G27*Параметры!$B$2*(1+'Модель SKU'!I10+Параметры!$B$8)+'Модель SKU'!H10+Параметры!$B$7 | I27: =F27/(1+Параметры!$B$3)-F27*Параметры!$B$4-'Модель SKU'!D10-'Модель SKU'!E10-F27*E27-F27*Параметры!$B$6-H27 | J27: =I27/F27 | K27: =I27*'Модель SKU'!V10
A28: ='Модель SKU'!A10 | B28: Оптимист: цена база, FOB −10%, PPC 8% | C28: 1 | D28: 0.9 | E28: 0.08 | F28: ='Модель SKU'!C10*C28 | G28: ='Модель SKU'!G10*D28 | H28: =G28*Параметры!$B$2*(1+'Модель SKU'!I10+Параметры!$B$8)+'Модель SKU'!H10+Параметры!$B$7 | I28: =F28/(1+Параметры!$B$3)-F28*Параметры!$B$4-'Модель SKU'!D10-'Модель SKU'!E10-F28*E28-F28*Параметры!$B$6-H28 | J28: =I28/F28 | K28: =I28*'Модель SKU'!V10

Sheet P&L пилота
A1: SKU | B1: Волна | C1: Партия, шт | D1: FOB $ итого | E1: Landed € итого (инвестиция в товар) | F1: Продано за 90 дней (разгон), шт | G1: Выручка 90д € | H1: Прибыль 90д € | I1: Возврат инвестиции за 90д, % | J1: Остаток стока, шт
A2: ='Модель SKU'!A2 | B2: ='Модель SKU'!B2 | C2: ='Модель SKU'!U2 | D2: ='Модель SKU'!G2*C2 | E2: ='Модель SKU'!N2*C2 | F2: =MIN(C2,ROUND('Модель SKU'!V2*3*Параметры!$B$11,0)) | G2: ='Модель SKU'!C2*F2 | H2: ='Модель SKU'!O2*F2 | I2: =H2/E2 | J2: =C2-F2
A3: ='Модель SKU'!A3 | B3: ='Модель SKU'!B3 | C3: ='Модель SKU'!U3 | D3: ='Модель SKU'!G3*C3 | E3: ='Модель SKU'!N3*C3 | F3: =MIN(C3,ROUND('Модель SKU'!V3*3*Параметры!$B$11,0)) | G3: ='Модель SKU'!C3*F3 | H3: ='Модель SKU'!O3*F3 | I3: =H3/E3 | J3: =C3-F3
A4: ='Модель SKU'!A4 | B4: ='Модель SKU'!B4 | C4: ='Модель SKU'!U4 | D4: ='Модель SKU'!G4*C4 | E4: ='Модель SKU'!N4*C4 | F4: =MIN(C4,ROUND('Модель SKU'!V4*3*Параметры!$B$11,0)) | G4: ='Модель SKU'!C4*F4 | H4: ='Модель SKU'!O4*F4 | I4: =H4/E4 | J4: =C4-F4
A5: ='Модель SKU'!A5 | B5: ='Модель SKU'!B5 | C5: ='Модель SKU'!U5 | D5: ='Модель SKU'!G5*C5 | E5: ='Модель SKU'!N5*C5 | F5: =MIN(C5,ROUND('Модель SKU'!V5*3*Параметры!$B$11,0)) | G5: ='Модель SKU'!C5*F5 | H5: ='Модель SKU'!O5*F5 | I5: =H5/E5 | J5: =C5-F5
A6: ='Модель SKU'!A6 | B6: ='Модель SKU'!B6 | C6: ='Модель SKU'!U6 | D6: ='Модель SKU'!G6*C6 | E6: ='Модель SKU'!N6*C6 | F6: =MIN(C6,ROUND('Модель SKU'!V6*3*Параметры!$B$11,0)) | G6: ='Модель SKU'!C6*F6 | H6: ='Модель SKU'!O6*F6 | I6: =H6/E6 | J6: =C6-F6
A7: ='Модель SKU'!A7 | B7: ='Модель SKU'!B7 | C7: ='Модель SKU'!U7 | D7: ='Модель SKU'!G7*C7 | E7: ='Модель SKU'!N7*C7 | F7: =MIN(C7,ROUND('Модель SKU'!V7*3*Параметры!$B$11,0)) | G7: ='Модель SKU'!C7*F7 | H7: ='Модель SKU'!O7*F7 | I7: =H7/E7 | J7: =C7-F7
A8: ='Модель SKU'!A8 | B8: ='Модель SKU'!B8 | C8: ='Модель SKU'!U8 | D8: ='Модель SKU'!G8*C8 | E8: ='Модель SKU'!N8*C8 | F8: =MIN(C8,ROUND('Модель SKU'!V8*3*Параметры!$B$11,0)) | G8: ='Модель SKU'!C8*F8 | H8: ='Модель SKU'!O8*F8 | I8: =H8/E8 | J8: =C8-F8
A9: ='Модель SKU'!A9 | B9: ='Модель SKU'!B9 | C9: ='Модель SKU'!U9 | D9: ='Модель SKU'!G9*C9 | E9: ='Модель SKU'!N9*C9 | F9: =MIN(C9,ROUND('Модель SKU'!V9*3*Параметры!$B$11,0)) | G9: ='Модель SKU'!C9*F9 | H9: ='Модель SKU'!O9*F9 | I9: =H9/E9 | J9: =C9-F9
A10: ='Модель SKU'!A10 | B10: ='Модель SKU'!B10 | C10: ='Модель SKU'!U10 | D10: ='Модель SKU'!G10*C10 | E10: ='Модель SKU'!N10*C10 | F10: =MIN(C10,ROUND('Модель SKU'!V10*3*Параметры!$B$11,0)) | G10: ='Модель SKU'!C10*F10 | H10: ='Модель SKU'!O10*F10 | I10: =H10/E10 | J10: =C10-F10
A11: ИТОГО | C11: =SUM(C2:C10) | D11: =SUM(D2:D10) | E11: =SUM(E2:E10) | F11: =SUM(F2:F10) | G11: =SUM(G2:G10) | H11: =SUM(H2:H10) | I11: =H11/E11 | J11: =SUM(J2:J10)

Sheet Cash-flow план
A1: Статья (план, €) | B1: Июл 26 | C1: Авг 26 | D1: Сен 26 | E1: Окт 26 | F1: Ноя 26 | G1: Дек 26 | H1: Янв 27 | I1: Фев 27 | J1: Мар 27 | K1: Апр 27 | L1: Май 27 | M1: Июн 27 | N1: Итого
A2: Образцы + экспресс (все SKU) | B2: -1200 | C2: 0 | D2: 0 | E2: 0 | F2: 0 | G2: 0 | H2: 0 | I2: 0 | J2: 0 | K2: 0 | L2: 0 | M2: 0 | N2: =SUM(B2:M2)
A3: Депозит 30% — Волна 1 + Страт | B3: -5160 | C3: 0 | D3: 0 | E3: 0 | F3: 0 | G3: 0 | H3: 0 | I3: 0 | J3: 0 | K3: 0 | L3: 0 | M3: 0 | N3: =SUM(B3:M3)
A4: Баланс 70% — Волна 1 + Страт | B4: 0 | C4: -12040 | D4: 0 | E4: 0 | F4: 0 | G4: 0 | H4: 0 | I4: 0 | J4: 0 | K4: 0 | L4: 0 | M4: 0 | N4: =SUM(B4:M4)
A5: Фрахт + пошлины + QC — Волна 1 | B5: 0 | C5: 0 | D5: -5000 | E5: 0 | F5: 0 | G5: 0 | H5: 0 | I5: 0 | J5: 0 | K5: 0 | L5: 0 | M5: 0 | N5: =SUM(B5:M5)
A6: Комплаенс (GPSR/LUCID/LFGB/OEKO/EUIPO) | B6: -3000 | C6: -2500 | D6: 0 | E6: 0 | F6: 0 | G6: 0 | H6: 0 | I6: 0 | J6: 0 | K6: 0 | L6: 0 | M6: 0 | N6: =SUM(B6:M6)
A7: Депозит 30% — Волна 2 | B7: 0 | C7: 0 | D7: 0 | E7: 0 | F7: -2290 | G7: 0 | H7: 0 | I7: 0 | J7: 0 | K7: 0 | L7: 0 | M7: 0 | N7: =SUM(B7:M7)
A8: Баланс 70% — Волна 2 | B8: 0 | C8: 0 | D8: 0 | E8: 0 | F8: 0 | G8: 0 | H8: -5340 | I8: 0 | J8: 0 | K8: 0 | L8: 0 | M8: 0 | N8: =SUM(B8:M8)
A9: Фрахт + пошлины + QC — Волна 2 | B9: 0 | C9: 0 | D9: 0 | E9: 0 | F9: 0 | G9: 0 | H9: 0 | I9: -2000 | J9: 0 | K9: 0 | L9: 0 | M9: 0 | N9: =SUM(B9:M9)
A10: Реинвест в сток (повторные заказы, landed) | B10: 0 | C10: 0 | D10: -4000 | E10: -7000 | F10: -10000 | G10: -12000 | H10: -14000 | I10: -16000 | J10: -18000 | K10: -20000 | L10: -21000 | M10: -21000 | N10: =SUM(B10:M10)
A11: PPC (по выручке, разгон) | B11: 0 | C11: 0 | D11: 0 | E11: -2100 | F11: -3500 | G11: -4900 | H11: -5600 | I11: -6300 | J11: -8400 | K11: -9900 | L11: -11100 | M11: -11800 | N11: =SUM(B11:M11)
A12: Поступления от продаж (выручка − сборы Amazon) | B12: 0 | C12: 0 | D12: 0 | E12: 10900 | F12: 18100 | G12: 25300 | H12: 29000 | I12: 32600 | J12: 42900 | K12: 49500 | L12: 56200 | M12: 58400 | N12: =SUM(B12:M12)
A13: Чистый поток месяца | B13: =SUM(B2:B12) | C13: =SUM(C2:C12) | D13: =SUM(D2:D12) | E13: =SUM(E2:E12) | F13: =SUM(F2:F12) | G13: =SUM(G2:G12) | H13: =SUM(H2:H12) | I13: =SUM(I2:I12) | ... M13: =SUM(M2:M12) | N13: =SUM(B13:M13)
A14: Кумулятивный поток | B14: =B13 | C14: =B14+C13 | D14: =C14+D13 | E14: =D14+E13 | F14: =E14+F13 | G14: =F14+G13 | H14: =G14+H13 | I14: =H14+I13 | J14: =I14+J13 | ... M14: =L14+M13
A16: План. Поступления = выручка − сборы Amazon (НДС/referral/FBA/возвраты); PPC и повторные закупки стока — отдельными строками. Разгон W1: окт 30% → мар 100% цели; W2: мар 30% → июн 100%. Кумулятив к июню 2027 ≈ +€78 тыс. — сходится с моделью прибыли. Пересчитать фактическими котировками после RFQ.
