Workbook
Name USD_AED: 'Параметры'!$B$3
Name VAT: 'Параметры'!$B$4
Name REF: 'Параметры'!$B$5
Name DUTY: 'Параметры'!$B$6
Name SEA: 'Параметры'!$B$7
Name FRTKG: 'Параметры'!$B$8
Name INBOUND: 'Параметры'!$B$9
Name RET: 'Параметры'!$B$10
Name MKT: 'Параметры'!$B$11
Name PPC_S: 'Параметры'!$B$12
Name COUP_S: 'Параметры'!$B$13
Name PPC_L: 'Параметры'!$B$14
Name COUP_L: 'Параметры'!$B$15
Name UAE_MKT: 'Параметры'!$B$16
Name SHARE: 'Параметры'!$B$17
Name CIT: 'Параметры'!$B$18

Sheet Параметры
A1: ПАРАМЕТРЫ МОДЕЛИ — редактируйте жёлтые ячейки, все расчёты пересчитаются автоматически
A2: Параметр | B2: Значение
A3: Курс USD→AED (фикс.) | B3: 3.6725
A4: НДС ОАЭ | B4: 0.05
A5: Referral fee (Home&Kitchen >50 AED) | B5: 0.15
A6: Таможенная пошлина ОАЭ (CIF) | B6: 0.05
A7: Фрахт море Китай→Джебель-Али, $/м³ | B7: 165
A8: Фрахт минимум, $/кг | B8: 0.45
A9: Приёмка/prep на FBA, AED/шт | B9: 2
A10: Резерв на возвраты | B10: 0.02
A11: Маркетинг (внешний/бренд) | B11: 0.03
A12: PPC/реклама — рабочий режим | B12: 0.12
A13: Купон/скидка — рабочий режим | B13: 0.03
A14: PPC/реклама — ЗАПУСК (ТЗ) | B14: 0.35
... A18: Налог на прибыль ОАЭ (>375k AED) | B18: 0.09
A20: МЕТОДИКА:
A21: • Источник спроса — новинки Amazon US (Home & Kitchen + мебель/офисные кресла), отслеживание с 2026.
A22: • Целевой рынок — Amazon.ae (ОАЭ), модель FBA. Цена ОАЭ = цена US × курс × наценка рынка (проверено по живым данным .ae).
A23: • 'Рабочий режим' — устойчивая экономика после разгона; 'ЗАПУСК' — повышенная реклама/скидки первые 2-3 мес (по ТЗ: PPC 35%, купон 10%).
A24: • FBA-сбор берётся из справочной таблицы (лист 'Справка_FBA'), поле редактируемое.
A25: • EBITDA/шт = Чистая выручка (без НДС) − (Referral + FBA + PPC + Купон + Маркетинг + Возвраты) − Landed COGS.
A26: • ROI = EBITDA/шт ÷ Landed COGS/шт. Маржа = EBITDA/шт ÷ Чистая выручка.
A27: • FOB и объём — ориентировочные (подтвердить RFQ у 3-5 поставщиков Alibaba).

Sheet Модель_ТЭО
A1: ТЕХНИКО-ЭКОНОМИЧЕСКОЕ ОБОСНОВАНИЕ — Amazon.ae (ОАЭ), FBA. Жёлтые/зелёные ячейки — ввод; серые — формулы.
A3: № | B3: Товар | C3: ASIN (кликаб.) | D3: Категория | E3: Цена US, $ | F3: Цена ОАЭ, AED | G3: Вес, кг | H3: Объём, м³ | I3: FOB $/шт | J3: FBA AED/шт | K3: Продажи US/мес | L3: Фрахт $/шт | M3: Пошлина $ | N3: Landed AED/шт | O3: Referral AED | P3: PPC AED | Q3: Купон AED | R3: Маркетинг AED | S3: Возвраты AED | T3: НДС AED | U3: Чист.выручка AED | V3: EBITDA/шт (режим) | W3: Маржа % (режим) | X3: ROI % (режим) | Y3: EBITDA/шт (запуск) | Z3: Маржа % (запуск) | AA3: Потенц. EBITDA/мес AED | AB3: Alibaba | AC3: Вердикт
A4: 1 | B4: Мини-вентилятор ручной турбо, аккумуляторный | C4: B0GKMVTD6V | D4: Охлаждение/вентиляторы | E4: 25.28 | F4: 104 | G4: 0.15 | H4: 0.0003 | I4: 5.5 | J4: 7.2 | K4: 10000 | L4: =MAX(H4*SEA,G4*FRTKG) | M4: =(I4+L4)*DUTY | N4: =(I4+L4+M4)*USD_AED+INBOUND | O4: =F4*REF | P4: =F4*PPC_S | Q4: =F4*COUP_S | R4: =F4*MKT | S4: =F4*RET | T4: =F4-F4/(1+VAT) | U4: =F4/(1+VAT) | V4: =U4-(O4+J4+P4+Q4+R4+S4)-N4 | W4: =V4/U4 | X4: =V4/N4 | Y4: =U4-(O4+J4+F4*PPC_L+F4*COUP_L+R4+S4)-N4 | Z4: =Y4/U4 | AA4: =V4*K4*UAE_MKT*SHARE | AB4: ссылка | AC4: ЗАПУСК
A5: 2 | B5: Вентилятор на шею безлопастной (носимый) | C5: B0GV2DHXWS | D5: Охлаждение/вентиляторы | E5: 30.15 | F5: 124 | G5: 0.37 | H5: 0.0028 | I5: 6.6 | J5: 8.5 | K5: 8000 | L5: =MAX(H5*SEA,G5*FRTKG) | M5: =(I5+L5)*DUTY | N5: =(I5+L5+M5)*USD_AED+INBOUND | O5: =F5*REF | P5: =F5*PPC_S | Q5: =F5*COUP_S | R5: =F5*MKT | S5: =F5*RET | T5: =F5-F5/(1+VAT) | U5: =F5/(1+VAT) | V5: =U5-(O5+J5+P5+Q5+R5+S5)-N5 | W5: =V5/U5 | X5: =V5/N5 | Y5: =U5-(O5+J5+F5*PPC_L+F5*COUP_L+R5+S5)-N5 | Z5: =Y5/U5 | AA5: =V5*K5*UAE_MKT*SHARE | AB5: ссылка | AC5: ЗАПУСК
A6: 3 | B6: Портативный кондиционер/охладитель воздуха | C6: B0GT8HK7LS | D6: Охлаждение/вентиляторы | E6: 54.24 | F6: 249 | G6: 1.01 | H6: 0.0086 | I6: 15.39 | J6: 14.5 | K6: 4000 | L6: =MAX(H6*SEA,G6*FRTKG) | M6: =(I6+L6)*DUTY | N6: =(I6+L6+M6)*USD_AED+INBOUND | O6: =F6*REF | P6: =F6*PPC_S | Q6: =F6*COUP_S | R6: =F6*MKT | S6: =F6*RET | T6: =F6-F6/(1+VAT) | U6: =F6/(1+VAT) | V6: =U6-(O6+J6+P6+Q6+R6+S6)-N6 | W6: =V6/U6 | X6: =V6/N6 | Y6: =U6-(O6+J6+F6*PPC_L+F6*COUP_L+R6+S6)-N6 | Z6: =Y6/U6 | AA6: =V6*K6*UAE_MKT*SHARE | AB6: ссылка | AC6: ЗАПУСК
A7: 4 | B7: Очиститель воздуха для дома (HEPA), большая комната | C7: B0GZVM23CF | D7: Климат/воздух | E7: 89.71 | F7: 369 | G7: 3.13 | H7: 0.0257 | I7: 25.2 | J7: 18.5 | K7: 8000 | L7: =MAX(H7*SEA,G7*FRTKG) | M7: =(I7+L7)*DUTY | N7: =(I7+L7+M7)*USD_AED+INBOUND | O7: =F7*REF | P7: =F7*PPC_S | Q7: =F7*COUP_S | R7: =F7*MKT | S7: =F7*RET | T7: =F7-F7/(1+VAT) | U7: =F7/(1+VAT) | V7: =U7-(O7+J7+P7+Q7+R7+S7)-N7 | W7: =V7/U7 | X7: =V7/N7 | Y7: =U7-(O7+J7+F7*PPC_L+F7*COUP_L+R7+S7)-N7 | Z7: =Y7/U7 | AA7: =V7*K7*UAE_MKT*SHARE | AB7: ссылка | AC7: ЗАПУСК
A8: 5 | B8: Осушитель воздуха для дома (~93 м²) | C8: B0H13ZY2W4 | D8: Климат/воздух | E8: 59.32 | F8: 244 | G8: 2.72 | H8: 0.0159 | I8: 16.8 | J8: 16.5 | K8: 4000 | L8: =MAX(H8*SEA,G8*FRTKG) | M8: =(I8+L8)*DUTY | N8: =(I8+L8+M8)*USD_AED+INBOUND | O8: =F8*REF | P8: =F8*PPC_S | Q8: =F8*COUP_S | R8: =F8*MKT | S8: =F8*RET | T8: =F8-F8/(1+VAT) | U8: =F8/(1+VAT) | V8: =U8-(O8+J8+P8+Q8+R8+S8)-N8 | W8: =V8/U8 | X8: =V8/N8 | Y8: =U8-(O8+J8+F8*PPC_L+F8*COUP_L+R8+S8)-N8 | Z8: =Y8/U8 | AA8: =V8*K8*UAE_MKT*SHARE | AB8: ссылка | AC8: ЗАПУСК
A9: 6 | B9: Ручной пароочиститель под давлением (110°C) | C9: B0GQHGFFHC | D9: Уборка/бытовая техника | E9: 70.26 | F9: 289 | G9: 1.82 | H9: 0.0096 | I9: 19.6 | J9: 14.5 | K9: 6000 | L9: =MAX(H9*SEA,G9*FRTKG) | M9: =(I9+L9)*DUTY | N9: =(I9+L9+M9)*USD_AED+INBOUND | O9: =F9*REF | P9: =F9*PPC_S | Q9: =F9*COUP_S | R9: =F9*MKT | S9: =F9*RET | T9: =F9-F9/(1+VAT) | U9: =F9/(1+VAT) | V9: =U9-(O9+J9+P9+Q9+R9+S9)-N9 | W9: =V9/U9 | X9: =V9/N9 | Y9: =U9-(O9+J9+F9*PPC_L+F9*COUP_L+R9+S9)-N9 | Z9: =Y9/U9 | AA9: =V9*K9*UAE_MKT*SHARE | AB9: ссылка | AC9: ЗАПУСК
A10: 7 | B10: Отпариватель для одежды 1000W портативный | C10: B0GJ4NHH4L | D10: Уборка/бытовая техника | E10: 49.6 | F10: 204 | G10: 0.99 | H10: 0.003 | I10: 13.99 | J10: 11 | K10: 4000 | L10: =MAX(H10*SEA,G10*FRTKG) | M10: =(I10+L10)*DUTY | N10: =(I10+L10+M10)*USD_AED+INBOUND | O10: =F10*REF | P10: =F10*PPC_S | Q10: =F10*COUP_S | R10: =F10*MKT | S10: =F10*RET | T10: =F10-F10/(1+VAT) | U10: =F10/(1+VAT) | V10: =U10-(O10+J10+P10+Q10+R10+S10)-N10 | W10: =V10/U10 | X10: =V10/N10 | Y10: =U10-(O10+J10+F10*PPC_L+F10*COUP_L+R10+S10)-N10 | Z10: =Y10/U10 | AA10: =V10*K10*UAE_MKT*SHARE | AB10: ссылка | AC10: ЗАПУСК
A11: 8 | B11: Ремни для переноски мебели (плечевые), 2 чел. | C11: B0GYF91BXB | D11: Хранение/организация | E11: 30.15 | F11: 124 | G11: 1.84 | H11: 0.0072 | I11: 6 | J11: 14.5 | K11: 30000 | L11: =MAX(H11*SEA,G11*FRTKG) | M11: =(I11+L11)*DUTY | N11: =(I11+L11+M11)*USD_AED+INBOUND | O11: =F11*REF | P11: =F11*PPC_S | Q11: =F11*COUP_S | R11: =F11*MKT | S11: =F11*RET | T11: =F11-F11/(1+VAT) | U11: =F11/(1+VAT) | V11: =U11-(O11+J11+P11+Q11+R11+S11)-N11 | W11: =V11/U11 | X11: =V11/N11 | Y11: =U11-(O11+J11+F11*PPC_L+F11*COUP_L+R11+S11)-N11 | Z11: =Y11/U11 | AA11: =V11*K11*UAE_MKT*SHARE | AB11: ссылка | AC11: ЗАПУСК
A12: 9 | B12: Вакуумные пакеты для хранения, 15 шт | C12: B0GSZHLZ3B | D12: Хранение/организация | E12: 33.79 | F12: 139 | G12: 1.18 | H12: 0.0067 | I12: 6.8 | J12: 14.5 | K12: 5000 | L12: =MAX(H12*SEA,G12*FRTKG) | M12: =(I12+L12)*DUTY | N12: =(I12+L12+M12)*USD_AED+INBOUND | O12: =F12*REF | P12: =F12*PPC_S | Q12: =F12*COUP_S | R12: =F12*MKT | S12: =F12*RET | T12: =F12-F12/(1+VAT) | U12: =F12/(1+VAT) | V12: =U12-(O12+J12+P12+Q12+R12+S12)-N12 | W12: =V12/U12 | X12: =V12/N12 | Y12: =U12-(O12+J12+F12*PPC_L+F12*COUP_L+R12+S12)-N12 | Z12: =Y12/U12 | AA12: =V12*K12*UAE_MKT*SHARE | AB12: ссылка | AC12: ЗАПУСК
A13: 10 | B13: Стойка для ванной телескопическая 4-ярусная (нерж.) | C13: B0GZZ3VM69 | D13: Хранение/организация | E13: 35.72 | F13: 164 | G13: 2.94 | H13: 0.0154 | I13: 7.2 | J13: 32 | K13: 6000 | L13: =MAX(H13*SEA,G13*FRTKG) | M13: =(I13+L13)*DUTY | N13: =(I13+L13+M13)*USD_AED+INBOUND | O13: =F13*REF | P13: =F13*PPC_S | Q13: =F13*COUP_S | R13: =F13*MKT | S13: =F13*RET | T13: =F13-F13/(1+VAT) | U13: =F13/(1+VAT) | V13: =U13-(O13+J13+P13+Q13+R13+S13)-N13 | W13: =V13/U13 | X13: =V13/N13 | Y13: =U13-(O13+J13+F13*PPC_L+F13*COUP_L+R13+S13)-N13 | Z13: =Y13/U13 | AA13: =V13*K13*UAE_MKT*SHARE | AB13: ссылка | AC13: ЗАПУСК
A14: 11 | B14: Корзина для белья с крышкой, складная 100 л | C14: B0G5DSK3YF | D14: Хранение/организация | E14: 19.94 | F14: 82 | G14: 1.12 | H14: 0.0061 | I14: 4 | J14: 14.5 | K14: 5000 | L14: =MAX(H14*SEA,G14*FRTKG) | M14: =(I14+L14)*DUTY | N14: =(I14+L14+M14)*USD_AED+INBOUND | O14: =F14*REF | P14: =F14*PPC_S | Q14: =F14*COUP_S | R14: =F14*MKT | S14: =F14*RET | T14: =F14-F14/(1+VAT) | U14: =F14/(1+VAT) | V14: =U14-(O14+J14+P14+Q14+R14+S14)-N14 | W14: =V14/U14 | X14: =V14/N14 | Y14: =U14-(O14+J14+F14*PPC_L+F14*COUP_L+R14+S14)-N14 | Z14: =Y14/U14 | AA14: =V14*K14*UAE_MKT*SHARE | AB14: ссылка | AC14: ЗАПУСК
A15: 12 | B15: Набор кухонных ножей 8 предметов (нерж., подставка) | C15: B0GCJQ4Z51 | D15: Кухня | E15: 30.15 | F15: 124 | G15: 1.16 | H15: 0.0065 | I15: 6.6 | J15: 14.5 | K15: 4000 | L15: =MAX(H15*SEA,G15*FRTKG) | M15: =(I15+L15)*DUTY | N15: =(I15+L15+M15)*USD_AED+INBOUND | O15: =F15*REF | P15: =F15*PPC_S | Q15: =F15*COUP_S | R15: =F15*MKT | S15: =F15*RET | T15: =F15-F15/(1+VAT) | U15: =F15/(1+VAT) | V15: =U15-(O15+J15+P15+Q15+R15+S15)-N15 | W15: =V15/U15 | X15: =V15/N15 | Y15: =U15-(O15+J15+F15*PPC_L+F15*COUP_L+R15+S15)-N15 | Z15: =Y15/U15 | AA15: =V15*K15*UAE_MKT*SHARE | AB15: ссылка | AC15: ЗАПУСК
... A23: 20 | B23: Коврик под офисное кресло (защита пола), XL | C23: B0G1SX2D8H | D23: Мебель/офисные аксессуары | E23: 55.33 | F23: 254 | G23: 4.08 | H23: 0.0048 | I23: 17.92 | J23: 32 | K23: 400 | L23: =MAX(H23*SEA,G23*FRTKG) | M23: =(I23+L23)*DUTY | N23: =(I23+L23+M23)*USD_AED+INBOUND | O23: =F23*REF | P23: =F23*PPC_S | Q23: =F23*COUP_S | R23: =F23*MKT | S23: =F23*RET | T23: =F23-F23/(1+VAT) | U23: =F23/(1+VAT) | V23: =U23-(O23+J23+P23+Q23+R23+S23)-N23 | W23: =V23/U23 | X23: =V23/N23 | Y23: =U23-(O23+J23+F23*PPC_L+F23*COUP_L+R23+S23)-N23 | Z23: =Y23/U23 | AA23: =V23*K23*UAE_MKT*SHARE | AB23: ссылка | AC23: ЗАПУСК
B24: ИТОГО портфель | AA24: =SUM(AA4:AA23)

Sheet Инвестиции
A1: ИНВЕСТИЦИОННЫЙ АНАЛИЗ (рабочий режим). Ввод: 'Заказ, шт' и бюджет запуска. Остальное — формулы.
A3: № | B3: Товар | C3: Заказ, шт | D3: Landed AED/шт | E3: Капитал закупки AED | F3: EBITDA/шт AED | G3: EBITDA/мес (при захвате) AED | H3: Окупаемость партии, мес
A4: 1 | B4: Мини-вентилятор ручной турбо, аккумуляторный | C4: 600 | D4: =Модель_ТЭО!N4 | E4: =C4*D4 | F4: =Модель_ТЭО!V4 | G4: =Модель_ТЭО!AA4 | H4: =IF(G4>0,E4/G4,"—")
A5: 2 | B5: Вентилятор на шею безлопастной (носимый) | C5: 500 | D5: =Модель_ТЭО!N5 | E5: =C5*D5 | F5: =Модель_ТЭО!V5 | G5: =Модель_ТЭО!AA5 | H5: =IF(G5>0,E5/G5,"—")
A6: 3 | B6: Портативный кондиционер/охладитель воздуха | C6: 300 | D6: =Модель_ТЭО!N6 | E6: =C6*D6 | F6: =Модель_ТЭО!V6 | G6: =Модель_ТЭО!AA6 | H6: =IF(G6>0,E6/G6,"—")
A7: 4 | B7: Очиститель воздуха для дома (HEPA), большая комната | C7: 300 | D7: =Модель_ТЭО!N7 | E7: =C7*D7 | F7: =Модель_ТЭО!V7 | G7: =Модель_ТЭО!AA7 | H7: =IF(G7>0,E7/G7,"—")
A8: 5 | B8: Осушитель воздуха для дома (~93 м²) | C8: 250 | D8: =Модель_ТЭО!N8 | E8: =C8*D8 | F8: =Модель_ТЭО!V8 | G8: =Модель_ТЭО!AA8 | H8: =IF(G8>0,E8/G8,"—")
A9: 6 | B9: Ручной пароочиститель под давлением (110°C) | C9: 300 | D9: =Модель_ТЭО!N9 | E9: =C9*D9 | F9: =Модель_ТЭО!V9 | G9: =Модель_ТЭО!AA9 | H9: =IF(G9>0,E9/G9,"—")
A10: 7 | B10: Отпариватель для одежды 1000W портативный | C10: 300 | D10: =Модель_ТЭО!N10 | E10: =C10*D10 | F10: =Модель_ТЭО!V10 | G10: =Модель_ТЭО!AA10 | H10: =IF(G10>0,E10/G10,"—")
A11: 8 | B11: Ремни для переноски мебели (плечевые), 2 чел. | C11: 1200 | D11: =Модель_ТЭО!N11 | E11: =C11*D11 | F11: =Модель_ТЭО!V11 | G11: =Модель_ТЭО!AA11 | H11: =IF(G11>0,E11/G11,"—")
A12: 9 | B12: Вакуумные пакеты для хранения, 15 шт | C12: 500 | D12: =Модель_ТЭО!N12 | E12: =C12*D12 | F12: =Модель_ТЭО!V12 | G12: =Модель_ТЭО!AA12 | H12: =IF(G12>0,E12/G12,"—")
A13: 10 | B13: Стойка для ванной телескопическая 4-ярусная (нерж.) | C13: 400 | D13: =Модель_ТЭО!N13 | E13: =C13*D13 | F13: =Модель_ТЭО!V13 | G13: =Модель_ТЭО!AA13 | H13: =IF(G13>0,E13/G13,"—")
A14: 11 | B14: Корзина для белья с крышкой, складная 100 л | C14: 400 | D14: =Модель_ТЭО!N14 | E14: =C14*D14 | F14: =Модель_ТЭО!V14 | G14: =Модель_ТЭО!AA14 | H14: =IF(G14>0,E14/G14,"—")
A15: 12 | B15: Набор кухонных ножей 8 предметов (нерж., подставка) | C15: 400 | D15: =Модель_ТЭО!N15 | E15: =C15*D15 | F15: =Модель_ТЭО!V15 | G15: =Модель_ТЭО!AA15 | H15: =IF(G15>0,E15/G15,"—")
... A23: 20 | B23: Коврик под офисное кресло (защита пола), XL | C23: 200 | D23: =Модель_ТЭО!N23 | E23: =C23*D23 | F23: =Модель_ТЭО!V23 | G23: =Модель_ТЭО!AA23 | H23: =IF(G23>0,E23/G23,"—")
B24: ИТОГО закупка (оборотный капитал) | E24: =SUM(E4:E23) | G24: =SUM(G4:G23)
B26: БЮДЖЕТ ЗАПУСКА (единовременно), AED
B27: Фотоконтент + A+ листинги (20 SKU) | E27: 18000
B28: Образцы + инспекция качества (QC) | E28: 14000
B29: Сертификация/регистрация (ESMA/G-mark, бренд) | E29: 22000
B30: Стартовая реклама PPC (буфер сверх юнит-экономики) | E30: 60000
B31: Логистика первой партии (буфер/страховка) | E31: 15000
B32: Резерв 10% | E32: =ROUND(SUM(E27:E31)*0.1,0)
B33: Итого бюджет запуска | E33: =SUM(E27:E32)
B35: ИТОГО СТАРТОВЫЕ ИНВЕСТИЦИИ (закупка + запуск), AED | E35: =E24+E33
B36: в USD | E36: =E35/USD_AED
B37: Потенциал EBITDA/мес (полный разгон), AED | E37: =G24
B38: Прибыль после налога ОАЭ 9% (в мес), AED | E38: =G24*(1-CIT)
B39: Окупаемость стартовых инвестиций, мес | E39: =E35/(G24*(1-CIT))
B40: ROI за 12 мес (годовая EBITDA после налога / инвестиции) | E40: =G24*(1-CIT)*12/E35

Sheet Справка_FBA
A1: СПРАВОЧНО: ориентировочная шкала FBA-сборов Amazon.ae (AED, 2026). Значения перенесите в столбец 'FBA AED/шт'.
A3: Тариф/категория | B3: AED/шт
A4: Стандарт ≤250 г | B4: 7.2
A5: Стандарт ≤500 г | B5: 8.5
A6: Стандарт ≤1 кг | B6: 11
A7: Стандарт ≤2 кг | B7: 14.5
A8: Стандарт ≤3 кг | B8: 16.5
A9: Стандарт ≤5 кг | B9: 18.5
A10: Стандарт ≤9 кг | B10: 20
A11: Стандарт ≤12 кг | B11: 21.5
A12: Крупногабарит ≤2 кг | B12: 25
A13: Крупногабарит ≤5 кг | B13: 32
A14: Крупногабарит ≤10 кг | B14: 41.5
A15: Тяж./объём ≤15 кг | B15: 60
... A18: Тяж./объём ≤30 кг | B18: 108
A19: Тяж./объём >30 кг | B19: 108 + 3/кг сверх 30
A21: Referral (комиссия) Home & Kitchen: 8% при цене ≤50 AED, 15% при >50 AED.
A22: НДС ОАЭ 5% включён в розничную цену (выделяется в модели).
A23: Пошлина ОАЭ 5% от CIF (FOB+фрахт).
A24: Пороги стандарт/крупногабарит зависят и от габаритов (длиннейшая сторона >45 см → крупногабарит).
A25: Точные тарифы — в FBA Revenue Calculator в Seller Central .ae (после входа).
