Workbook

Sheet Модель
A1: ФИН-МОДЕЛЬ: Health Products — США → ОАЭ
A2: Жёлтые ячейки — вводишь свои данные. Зелёные — считаются сами.
A4: 1. КУРС И ЦЕЛЬ
A5: Курс USD → AED | B5: 3.6725 | C5: дирхам привязан к доллару (~3.6725)
A6: Целевая ЧИСТАЯ прибыль, AED/мес | B6: 3500 | C6: «на руки» — из ТЗ ≈ 3 500 AED
A7: Целевой ОБОРОТ, AED/мес (альтерн. цель) | B7: 10000 | C7: из ТЗ — 10 000 AED выручки
A9: 2. ЮНИТ-ЭКОНОМИКА (на 1 шт, в AED)
A10: Цена продажи на amazon.ae / noon, AED | B10: 150 | C10: розничная цена за 1 шт
A11: Себестоимость landed (завод+логистика в ОАЭ), AED | B11: 40 | C11: закупка + доставка + растаможка на 1 шт
A12: Реферальная комиссия Amazon, % | B12: 0.15 | C12: Health/Beauty на amazon.ae ≈ 8–15%
A13: Фулфилмент FBA, AED/шт | B13: 15 | C13: pick&pack + вес; лёгкий товар дешевле
A14: Реклама PPC, AED/шт | B14: 15 | C14: бюджет продвижения на 1 проданную шт
A15: Возвраты + прочее, % от цены | B15: 0.03 | C15: брак, возвраты, упаковка
A16: НДС (VAT) ОАЭ, % | B16: 0.05 | C16: 5% — собирается сверху и перечисляется, в прибыль НЕ идёт
A17: → Реферальная комиссия, AED | B17: =B10*B12
A18: → Возвраты/прочее, AED | B18: =B10*B15
A19: → ВАЛОВАЯ прибыль с 1 шт, AED | B19: =B10-B11-B17-B13-B14-B18 | C19: цена минус все переменные затраты (без НДС)
A20: → Маржа, % от цены | B20: =B19/B10 | C20: цель по ТЗ: ≥ 30%
A21: → Проверка маржи (≥30%?) | B21: =IF(B20>=0.3,"✅ OK (≥30%)","⚠️ ниже 30% — поднять цену / снизить COGS")
A23: 3. СКОЛЬКО ПРОДАВАТЬ (расчёт объёма)
A24: Фикс. расходы, AED/мес | B24: 300 | C24: хранение, подписка seller, сервисы
A25: Юнитов/мес для целевой ПРИБЫЛИ | B25: =ROUNDUP((B6+B24)/B19,0) | C25: =(цель прибыли + фикс) / валовая прибыль с шт
A26: → Оборот при этом объёме, AED/мес | B26: =B25*B10
A27: Юнитов/мес для целевого ОБОРОТА | B27: =ROUNDUP(B7/B10,0) | C27: =целевой оборот / цена
A28: → Чистая прибыль при этом обороте, AED/мес | B28: =B27*B19-B24
A30: 4. ПРОВЕРКА СПРОСА: США → ОАЭ (÷ коэффициент)
A31: Продажи в США, шт/мес (из Keepa) | B31: 10000 | C31: monthly_sold конкретного товара/ниши
A32: Понижающий коэффициент США→ОАЭ | B32: 40 | C32: из ТЗ: 2000 в США → 50 в ОАЭ = ÷40
A33: → Оценка спроса ОАЭ, шт/мес (весь рынок) | B33: =ROUND(B31/B32,0) | C33: весь объём ниши в ОАЭ, не наш
A34: → Наша доля рынка для цели по прибыли | B34: =B25/B33 | C34: какую долю ниши надо взять
A35: → ВЕРДИКТ по реалистичности | B35: =IF(B25<=B33*0.3,"✅ РЕАЛЬНО (нужно ≤30% ниши)",IF(B25<=B33,"⚠️ НАПРЯЖНО (нужна большая доля ниши)","❌ НЕ ВЛЕЗАЕМ (спрос ОАЭ меньше цели)"))
A37: 5. ЗАКУПКА (первая партия)
A38: На сколько месяцев берём запас | B38: 2 | C38: 1-я партия обычно на 1.5–2.5 мес
A39: Юнитов заказать (по цели прибыли) | B39: =ROUNDUP(B25*B38,0)
A40: Капитал на партию, AED | B40: =B39*B11 | C40: =юнитов × себестоимость
A41: → то же в USD | B41: =B40/B5
A42: Окупаемость партии, мес | B42: =B40/(B25*B19) | C42: капитал / валовая прибыль в мес
A45: Как читать: заполни жёлтые ячейки (цена, себестоимость, продажи в США, коэффициент). Строка «Юнитов/мес для целевой ПРИБЫЛИ» и «ВЕРДИКТ по реалистичности» — главный ответ. Если вердикт ❌/⚠️ — снижай цель, поднимай цену/маржу или бери коэффициент реалистичнее.

Sheet Сценарии
A1: СЦЕНАРИИ — сколько юнитов/мес нужно для цели по прибыли
A2: Все формулы тянут вход с листа «Модель». Меняешь там — тут пересчитывается.
A4: A. Юнитов/мес для цели по прибыли — при разной цене и марже
A5: Цена, AED \ Маржа → | B5: 0.2 | C5: 0.25 | D5: 0.3 | E5: 0.35 | F5: 0.4 | G5: 0.5
A6: 50 | B6: =ROUNDUP((Модель!B6+Модель!B24)/(A6*B5),0) | C6: =ROUNDUP((Модель!B6+Модель!B24)/(A6*C5),0) | D6: =ROUNDUP((Модель!B6+Модель!B24)/(A6*D5),0) | E6: =ROUNDUP((Модель!B6+Модель!B24)/(A6*E5),0) | F6: =ROUNDUP((Модель!B6+Модель!B24)/(A6*F5),0) | G6: =ROUNDUP((Модель!B6+Модель!B24)/(A6*G5),0)
A7: 70 | B7: =ROUNDUP((Модель!B6+Модель!B24)/(A7*B5),0) | C7: =ROUNDUP((Модель!B6+Модель!B24)/(A7*C5),0) | D7: =ROUNDUP((Модель!B6+Модель!B24)/(A7*D5),0) | E7: =ROUNDUP((Модель!B6+Модель!B24)/(A7*E5),0) | F7: =ROUNDUP((Модель!B6+Модель!B24)/(A7*F5),0) | G7: =ROUNDUP((Модель!B6+Модель!B24)/(A7*G5),0)
A8: 90 | B8: =ROUNDUP((Модель!B6+Модель!B24)/(A8*B5),0) | C8: =ROUNDUP((Модель!B6+Модель!B24)/(A8*C5),0) | D8: =ROUNDUP((Модель!B6+Модель!B24)/(A8*D5),0) | E8: =ROUNDUP((Модель!B6+Модель!B24)/(A8*E5),0) | F8: =ROUNDUP((Модель!B6+Модель!B24)/(A8*F5),0) | G8: =ROUNDUP((Модель!B6+Модель!B24)/(A8*G5),0)
A9: 120 | B9: =ROUNDUP((Модель!B6+Модель!B24)/(A9*B5),0) | C9: =ROUNDUP((Модель!B6+Модель!B24)/(A9*C5),0) | D9: =ROUNDUP((Модель!B6+Модель!B24)/(A9*D5),0) | E9: =ROUNDUP((Модель!B6+Модель!B24)/(A9*E5),0) | F9: =ROUNDUP((Модель!B6+Модель!B24)/(A9*F5),0) | G9: =ROUNDUP((Модель!B6+Модель!B24)/(A9*G5),0)
A10: 150 | B10: =ROUNDUP((Модель!B6+Модель!B24)/(A10*B5),0) | C10: =ROUNDUP((Модель!B6+Модель!B24)/(A10*C5),0) | D10: =ROUNDUP((Модель!B6+Модель!B24)/(A10*D5),0) | E10: =ROUNDUP((Модель!B6+Модель!B24)/(A10*E5),0) | F10: =ROUNDUP((Модель!B6+Модель!B24)/(A10*F5),0) | G10: =ROUNDUP((Модель!B6+Модель!B24)/(A10*G5),0)
A11: 200 | B11: =ROUNDUP((Модель!B6+Модель!B24)/(A11*B5),0) | C11: =ROUNDUP((Модель!B6+Модель!B24)/(A11*C5),0) | D11: =ROUNDUP((Модель!B6+Модель!B24)/(A11*D5),0) | E11: =ROUNDUP((Модель!B6+Модель!B24)/(A11*E5),0) | F11: =ROUNDUP((Модель!B6+Модель!B24)/(A11*F5),0) | G11: =ROUNDUP((Модель!B6+Модель!B24)/(A11*G5),0)
A14: B. Оценка спроса ОАЭ (шт/мес) при разных продажах в США и коэффициенте
A15: Продажи США, шт/мес \ ÷K → | B15: 20 | C15: 30 | D15: 40 | E15: 60 | F15: 80 | G15: 100
A16: 1000 | B16: =ROUND(A16/B15,0) | C16: =ROUND(A16/C15,0) | D16: =ROUND(A16/D15,0) | E16: =ROUND(A16/E15,0) | F16: =ROUND(A16/F15,0) | G16: =ROUND(A16/G15,0)
A17: 2000 | B17: =ROUND(A17/B15,0) | C17: =ROUND(A17/C15,0) | D17: =ROUND(A17/D15,0) | E17: =ROUND(A17/E15,0) | F17: =ROUND(A17/F15,0) | G17: =ROUND(A17/G15,0)
A18: 3000 | B18: =ROUND(A18/B15,0) | C18: =ROUND(A18/C15,0) | D18: =ROUND(A18/D15,0) | E18: =ROUND(A18/E15,0) | F18: =ROUND(A18/F15,0) | G18: =ROUND(A18/G15,0)
A19: 5000 | B19: =ROUND(A19/B15,0) | C19: =ROUND(A19/C15,0) | D19: =ROUND(A19/D15,0) | E19: =ROUND(A19/E15,0) | F19: =ROUND(A19/F15,0) | G19: =ROUND(A19/G15,0)
A20: 8000 | B20: =ROUND(A20/B15,0) | C20: =ROUND(A20/C15,0) | D20: =ROUND(A20/D15,0) | E20: =ROUND(A20/E15,0) | F20: =ROUND(A20/F15,0) | G20: =ROUND(A20/G15,0)
A21: 10000 | B21: =ROUND(A21/B15,0) | C21: =ROUND(A21/C15,0) | D21: =ROUND(A21/D15,0) | E21: =ROUND(A21/E15,0) | F21: =ROUND(A21/F15,0) | G21: =ROUND(A21/G15,0)
A23: Сравни числа из таблицы B (спрос всей ниши в ОАЭ) с «Юнитов/мес для прибыли» из таблицы A. Если нужное число юнитов больше спроса ниши — цель нереальна.

Sheet Кандидаты US→ОАЭ
A1: Ниша (БЕЗ БАД) | B1: Пример (бренд) | C1: ASIN | D1: Цена US, $ | E1: Цена US, AED | F1: Продажи US, шт/мес | G1: Оценка ОАЭ ÷40, шт/мес | H1: Отзывы | I1: Офферов | J1: Регистрация в ОАЭ | K1: Барьер входа | L1: Комментарий
A2: Бандаж запястья / карпал-туннель | B2: FREETOO | C2: B0DNFTL63F | D2: 19.95 | E2: =D2*3.6725 | F2: 3000 | G2: =ROUND(F2/40,0) | H2: 5704 | I2: 1 | J2: нет (обычный товар) | K2: Низкий | L2: ★ Не БАД, не мед.прибор. Лёгкий, private-label легко. У бренда 5+ SKU-вариантов (левая/правая рука).
A3: Аптечка / First Aid Kit | B3: First Aid Only | C3: B08P27LHJ4 | D3: 20.95 | E3: =D3*3.6725 | F3: 10000 | G3: =ROUND(F3/40,0) | H3: 5658 | I3: 1 | J3: нет (набор расходников) | K3: Низкий | L3: ★ Высокий спрос, не БАД. Габарит больше — заложи FBA/логистику.
A4: Органические прокладки | B4: This is L. | C4: B0DR3BYKWC | D4: 22.99 | E4: =D4*3.6725 | F4: 5000 | G4: =ROUND(F4/40,0) | H4: 1091 | I4: 3 | J4: нет (гигиена) | K4: Низкий | L4: ★ Не БАД. Женская гигиена, органик-ниша растёт, повторные покупки.
A5: Органические прокладки/тампоны | B5: Honey Pot | C5: B0DCDPBZX2 | D5: 22.99 | E5: =D5*3.6725 | F5: 2000 | G5: =ROUND(F5/40,0) | H5: 1366 | I5: 2 | J5: нет (гигиена) | K5: Низкий | L5: Органик женская гигиена, свежий бренд, лёгкая логистика.
A6: Отбеливание зубов (гель+каппа) | B6: Opalescence | C6: B000MMYI8G | D6: 28.98 | E6: =D6*3.6725 | F6: 10000 | G6: =ROUND(F6/40,0) | H6: 3439 | I6: 1 | J6: космет. рег. (легче БАД) | K6: Средний | L6: Оральная косметика — регистрация проще БАД, но нужна. Высокий спрос.
A7: Зубная паста гидроксиапатит | B7: Himalaya | C7: B0C4MMPCQH | D7: 19.59 | E7: =D7*3.6725 | F7: 1000 | G7: =ROUND(F7/40,0) | H7: 3699 | I7: 1 | J7: космет. рег. | K7: Средний | L7: Fluoride-free тренд, оральная косметика.
A8: Повязка на рану (Xeroform) | B8: Dr. Med | C8: B0BGXMXNRD | D8: 25.99 | E8: =D8*3.6725 | F8: 1000 | G8: =ROUND(F8/40,0) | H8: 1292 | I8: 1 | J8: мед.изделие (MOHAP) | K8: Высокий | L8: Раневые повязки = мед.изделие → регистрация MOHAP. Не БАД, но барьер есть.
A9: Флашбл-салфетки (гигиена) | B9: DUDE Wipes | C9: B0GFFLR222 | D9: 16.98 | E9: =D9*3.6725 | F9: 9000 | G9: =ROUND(F9/40,0) | H9: 241600 | I9: 1 | J9: нет (гигиена) | K9: Высокий | L9: Спрос огромный, но бренд-война (DUDE/Cottonelle) — тяжело зайти новичку.
A10: СМЕЖНЫЕ НЕ-БАД НИШИ К ПРОВЕРКЕ (запусти title-поиск в Keepa)
A11: Корректор осанки (posture) | J11: нет (обычный товар) | K11: Низкий | L11: Классика private-label, лёгкий, вирусится в соцсетях.
A12: Наколенник / налокотник / бандаж | J12: нет (обычный товар) | K12: Низкий | L12: Спорт/восстановление, много под-SKU по размерам.
A13: Компрессионные носки / рукава | J13: нет (обычный товар) | K13: Низкий | L13: Тревел/спорт/варикоз, лёгкий, дёшев в логистике.
A14: Ортопедические стельки | J14: нет (обычный товар) | K14: Низкий | L14: Расходка, повторные покупки, лёгкие.
A15: Массажный коврик (акупрессура) | J15: нет (обычный товар) | K15: Низкий | L15: Не электро; смотри объёмный вес для FBA.
A16: Органайзер для таблеток | J16: нет (обычный товар) | K16: Низкий | L16: Пластик, дёшево, стабильный спрос, лёгкий.
A17: Массаж-пистолет / ролик | J17: эл.прибор (G-mark/сертиф.) | K17: Средний | L17: Электроника → сертификация ОАЭ (G-mark). Высокий чек.
A18: Грелка электрическая (heating pad) | J18: эл.прибор (G-mark/сертиф.) | K18: Средний | L18: Электроника → сертификация. Сезонность.
A20: ★ = приоритет для НОВОГО продавца: спрос есть, вход дешевле, БЕЗ регистрации. ВАЖНО: «не БАД» ≠ «без регистрации» — мед.изделия (повязки, тонометры, TENS) → MOHAP; электроника (массажёры, грелки) → сертификация; оральная косметика → космет.регистрация. Самый лёгкий путь — бандажи/компрессия/гигиена/стельки/органайзеры.

Sheet Инструкция
A1: ИНСТРУКЦИЯ И ДОПУЩЕНИЯ
A3: КАК ПОЛЬЗОВАТЬСЯ
A4: 1. Открой лист «Модель». Заполни ЖЁЛТЫЕ ячейки: цена, себестоимость landed, комиссии, реклама.
A5: 2. Внизу впиши «Продажи в США, шт/мес» (из Keepa по конкретному товару) и коэффициент США→ОАЭ.
A6: 3. Смотри ответы: «Юнитов/мес для целевой прибыли», «ВЕРДИКТ по реалистичности», «Капитал на партию».
A7: 4. Лист «Сценарии» — таблицы чувствительности (цена×маржа и продажи США×коэффициент).
A8: 5. Лист «Кандидаты US→ОАЭ» — реальные товары из Keepa с оценкой спроса ОАЭ и барьером входа.
A10: МЕТОДОЛОГИЯ (по ТЗ)
A11: • Шаг 1 — проверяем товар в США (Keepa даёт реальные monthly_sold, рейтинг, конкуренцию).
A12: • Шаг 2 — ОАЭ = основной рынок, но объём меньше: масштабируем ÷K (в ТЗ пример 2000→50, т.е. ÷40).
A13: • Шаг 3 — считаем юнит-экономику и сколько штук нужно продать для цели 10 000 AED / 3 500 AED прибыли.
A14: • Шаг 4 — маржа от 30%: модель подсвечивает, добита ли планка 30%.
... A43: • Dubai Municipality / MOHAP — требования к регистрации БАД (freyr, artixio, dm.gov.ae).
